{
    "header": [
        " *   ",
        " *   如非需要调试，本文件可删除",
        " *   非专业人员可将本文件删除",
        " *   详细介绍请参考: https://bazhan.wang/faq#INFO-JSON",
        " *   "
    ],
    "resources": [
        {
            "url": "https://www.xlink.cn/products/v8/",
            "path": "index.html",
            "saved": true,
            "size": 91033,
            "children": [
                {
                    "url": "https://www.xlink.cn/_nuxt/fonts/iconfont.392feb5.woff2",
                    "path": "fonts/iconfont.392feb5.woff2",
                    "saved": true,
                    "size": 0,
                    "children": []
                },
                {
                    "url": "https://www.xlink.cn/_nuxt/fonts/iconfont.81bac9d.woff",
                    "path": "fonts/iconfont.81bac9d.woff",
                    "saved": true,
                    "size": 0,
                    "children": []
                },
                {
                    "url": "https://www.xlink.cn/_nuxt/fonts/iconfont.e0802e5.ttf",
                    "path": "fonts/iconfont.e0802e5.ttf",
                    "saved": true,
                    "size": 0,
                    "children": []
                },
                {
                    "url": "https://www.xlink.cn/_nuxt/img/contact-us.de1aed4.png",
                    "path": "img/contact-us.de1aed4.png",
                    "saved": true,
                    "size": 0,
                    "children": []
                },
                {
                    "url": "https://www.xlink.cn/_nuxt/img/contact-us-disabled.9fde754.png",
                    "path": "img/contact-us-disabled.9fde754.png",
                    "saved": true,
                    "size": 0,
                    "children": []
                },
                {
                    "url": "https://www.xlink.cn/_nuxt/img/1.1470640.png",
                    "path": "img/1.1470640.png",
                    "saved": true,
                    "size": 0,
                    "children": []
                },
                {
                    "url": "https://www.xlink.cn/_nuxt/img/2.707cf4d.png",
                    "path": "img/2.707cf4d.png",
                    "saved": true,
                    "size": 0,
                    "children": []
                },
                {
                    "url": "https://www.xlink.cn/_nuxt/img/3.fe899bc.png",
                    "path": "img/3.fe899bc.png",
                    "saved": true,
                    "size": 0,
                    "children": []
                },
                {
                    "url": "https://www.xlink.cn/_nuxt/img/4.0192168.png",
                    "path": "img/4.0192168.png",
                    "saved": true,
                    "size": 0,
                    "children": []
                },
                {
                    "url": "https://www.xlink.cn/_nuxt/img/5.a9f9867.png",
                    "path": "img/5.a9f9867.png",
                    "saved": true,
                    "size": 0,
                    "children": []
                },
                {
                    "url": "https://www.xlink.cn/_nuxt/img/6.6caa02a.png",
                    "path": "img/6.6caa02a.png",
                    "saved": true,
                    "size": 0,
                    "children": []
                },
                {
                    "url": "https://www.xlink.cn/_nuxt/img/form-bg.13f7dca.png",
                    "path": "img/form-bg.13f7dca.png",
                    "saved": true,
                    "size": 0,
                    "children": []
                },
                {
                    "url": "https://www.xlink.cn/_nuxt/img/icon-consult.034cf79.png",
                    "path": "img/icon-consult.034cf79.png",
                    "saved": true,
                    "size": 0,
                    "children": []
                },
                {
                    "url": "https://www.xlink.cn/_nuxt/img/icon-follow.4de853c.png",
                    "path": "img/icon-follow.4de853c.png",
                    "saved": true,
                    "size": 0,
                    "children": []
                },
                {
                    "url": "https://www.xlink.cn/_nuxt/img/icon-contact.84303c6.png",
                    "path": "img/icon-contact.84303c6.png",
                    "saved": true,
                    "size": 0,
                    "children": []
                },
                {
                    "url": "https://www.xlink.cn/_nuxt/img/banner.fdec48b.png",
                    "path": "img/banner.fdec48b.png",
                    "saved": true,
                    "size": 0,
                    "children": []
                },
                {
                    "url": "https://www.xlink.cn/_nuxt/img/logo_xs.fb0353a.png",
                    "path": "img/logo_xs.fb0353a.png",
                    "saved": true,
                    "size": 0,
                    "children": []
                },
                {
                    "url": "https://www.xlink.cn/_nuxt/img/logo.65357b3.png",
                    "path": "img/logo.65357b3.png",
                    "saved": true,
                    "size": 0,
                    "children": []
                },
                {
                    "url": "https://www.xlink.cn/_nuxt/img/structure.2208054.png",
                    "path": "img/structure.2208054.png",
                    "saved": true,
                    "size": 0,
                    "children": []
                },
                {
                    "url": "https://www.xlink.cn/_nuxt/img/1.db3b1ea.png",
                    "path": "img/1.db3b1ea.png",
                    "saved": true,
                    "size": 0,
                    "children": []
                },
                {
                    "url": "https://www.xlink.cn/_nuxt/img/2.ecd5974.png",
                    "path": "img/2.ecd5974.png",
                    "saved": true,
                    "size": 0,
                    "children": []
                },
                {
                    "url": "https://www.xlink.cn/_nuxt/img/3.e4de43a.png",
                    "path": "img/3.e4de43a.png",
                    "saved": true,
                    "size": 0,
                    "children": []
                },
                {
                    "url": "https://www.xlink.cn/_nuxt/img/4.9310233.png",
                    "path": "img/4.9310233.png",
                    "saved": true,
                    "size": 0,
                    "children": []
                },
                {
                    "url": "https://www.xlink.cn/_nuxt/img/5.f87b50c.png",
                    "path": "img/5.f87b50c.png",
                    "saved": true,
                    "size": 0,
                    "children": []
                },
                {
                    "url": "https://www.xlink.cn/_nuxt/img/6.c10e653.png",
                    "path": "img/6.c10e653.png",
                    "saved": true,
                    "size": 0,
                    "children": []
                },
                {
                    "url": "https://www.xlink.cn/_nuxt/img/7.8a9fa67.png",
                    "path": "img/7.8a9fa67.png",
                    "saved": true,
                    "size": 0,
                    "children": []
                },
                {
                    "url": "https://www.xlink.cn/_nuxt/img/8.0e3999b.png",
                    "path": "img/8.0e3999b.png",
                    "saved": true,
                    "size": 0,
                    "children": []
                },
                {
                    "url": "https://www.xlink.cn/_nuxt/img/smart-community.3a3983b.png",
                    "path": "img/smart-community.3a3983b.png",
                    "saved": true,
                    "size": 0,
                    "children": []
                },
                {
                    "url": "https://www.xlink.cn/_nuxt/img/smart-park.6564355.png",
                    "path": "img/smart-park.6564355.png",
                    "saved": true,
                    "size": 0,
                    "children": []
                },
                {
                    "url": "https://www.xlink.cn/_nuxt/img/smart-business.0a8e2ef.png",
                    "path": "img/smart-business.0a8e2ef.png",
                    "saved": true,
                    "size": 0,
                    "children": []
                },
                {
                    "url": "https://www.xlink.cn/_nuxt/img/more-spaces.1a9aa4d.png",
                    "path": "img/more-spaces.1a9aa4d.png",
                    "saved": true,
                    "size": 0,
                    "children": []
                },
                {
                    "url": "https://www.xlink.cn/_nuxt/img/foot-logo.749e7db.png",
                    "path": "img/foot-logo.749e7db.png",
                    "saved": true,
                    "size": 0,
                    "children": []
                },
                {
                    "url": "https://www.xlink.cn/_nuxt/img/weixin-qrcode.b50c196.jpg",
                    "path": "img/weixin-qrcode.b50c196.jpeg",
                    "saved": true,
                    "size": 0,
                    "children": []
                },
                {
                    "url": "https://www.xlink.cn/breakpoints.min.js",
                    "path": "js/breakpoints.min.js",
                    "saved": true,
                    "size": 7384,
                    "children": []
                },
                {
                    "url": "https://www.xlink.cn/_nuxt/static/1669692298/products/v8/state.js",
                    "path": "js/state.js",
                    "saved": true,
                    "size": 415,
                    "children": []
                },
                {
                    "url": "https://www.xlink.cn/_nuxt/778a25b.js",
                    "path": "js/778a25b.js",
                    "saved": true,
                    "size": 3564,
                    "children": []
                },
                {
                    "url": "https://www.xlink.cn/_nuxt/a87ce89.js",
                    "path": "js/a87ce89.js",
                    "saved": true,
                    "size": 0,
                    "children": []
                },
                {
                    "url": "https://www.xlink.cn/_nuxt/5a3d3a0.js",
                    "path": "js/5a3d3a0.js",
                    "saved": true,
                    "size": 11182,
                    "children": []
                },
                {
                    "url": "https://www.xlink.cn/_nuxt/c2cb916.js",
                    "path": "js/c2cb916.js",
                    "saved": true,
                    "size": 0,
                    "children": []
                },
                {
                    "url": "https://www.xlink.cn/_nuxt/5f781aa.js",
                    "path": "js/5f781aa.js",
                    "saved": true,
                    "size": 0,
                    "children": []
                },
                {
                    "url": "https://www.xlink.cn/_nuxt/41063e1.js",
                    "path": "js/41063e1.js",
                    "saved": true,
                    "size": 0,
                    "children": []
                },
                {
                    "url": "https://www.xlink.cn/favicon.ico",
                    "path": "favicon.ico",
                    "saved": true,
                    "size": 0,
                    "children": []
                }
            ]
        }
    ],
    "alias": "www-xlink-cn-2exewc2a",
    "info": {
        "remark": [],
        "title": "V8-智慧视频|云智易-智慧物联",
        "domain": "www.xlink.cn",
        "origin": "https://www.xlink.cn",
        "ip": "47.97.207.198",
        "main": "index.html",
        "url": "https://www.xlink.cn/products/v8/",
        "totalSize": "114 kB",
        "request": {
            "headers": {
                "accept": "text/html,*/*",
                "accept-language": "zh-CN,zh;q=0.9",
                "cache-control": "no-cache",
                "cookie": "",
                "referer": "https://www.xlink.cn/products/v8/",
                "user-agent": "Mozilla/5.0 (Windows NT 10.0; Win64; x64) AppleWebKit/537.36 (KHTML, like Gecko) Chrome/78.0.3904.108 Safari/537.36",
                "x-scraper-website": "https://bazhan.wang/"
            }
        },
        "response": {
            "responseUrl": "https://www.xlink.cn/products/v8/",
            "redirects": [],
            "statusCode": 200,
            "headers": {
                "date": "Tue, 13 Dec 2022 07:49:43 GMT",
                "content-type": "text/html; charset=UTF-8",
                "content-length": "93065",
                "connection": "close",
                "vary": "Accept-Encoding, Accept-Encoding",
                "accept-ranges": "bytes",
                "cache-control": "public, max-age=0",
                "last-modified": "Tue, 29 Nov 2022 03:25:02 GMT",
                "etag": "W/\"16b89-184c16aa2b0\""
            }
        },
        "time": {
            "start": "2022-12-13T07:49:43.310Z",
            "end": "2022-12-13T07:49:48.287Z"
        }
    },
    "options": {
        "url": "https://www.xlink.cn/products/v8/",
        "referer": "",
        "cookies": "",
        "userAgent": "Mozilla/5.0 (Windows NT 10.0; Win64; x64) AppleWebKit/537.36 (KHTML, like Gecko) Chrome/78.0.3904.108 Safari/537.36",
        "formatter": [],
        "filenameGenerator": "byType"
    }
}